custom_conda_create/__init__.py
custom_conda_create/cli.py
custom_conda_create/custom_conda_create.py
custom_conda_create-0.1.0.dist-info/METADATA
custom_conda_create-0.1.0.dist-info/RECORD
custom_conda_create-0.1.0.dist-info/WHEEL
custom_conda_create-0.1.0.dist-info/entry_points.txt
custom_conda_create-0.1.0.dist-info/top_level.txt
