Metadata-Version: 2.1
Name: custom-conda-create
Version: 0.1.0
Summary: Small CLI tool that customizes the conda create command.
Home-page: https://github.com/bk-m/custom_conda_create
Author: Bjoern Kolja Mielsch
Author-email: kolja.mielsch@gmail.com
License: MIT license
Keywords: custom_conda_create
Platform: UNKNOWN
Classifier: Development Status :: 2 - Pre-Alpha
Classifier: Intended Audience :: Developers
Classifier: License :: OSI Approved :: MIT License
Classifier: Natural Language :: English
Classifier: Programming Language :: Python :: 3
Classifier: Programming Language :: Python :: 3.4
Classifier: Programming Language :: Python :: 3.5
Classifier: Programming Language :: Python :: 3.6
Requires-Dist: Click (>=6.7)
